<toc version="2.0">
  <tocitem target="tasks-topic-group" text="GlassFish Server &#44288;&#47532; &#53080;&#49556; &#51089;&#50629;" expand="false">
    <tocitem target="task-group-configwebcontainer" text="&#50937; &#52968;&#53580;&#51060;&#45320; &#44396;&#49457;" expand="false">
      <tocitem target="task-webcontainergeneral" text="&#50937; &#52968;&#53580;&#51060;&#45320;&#51032; &#51068;&#48152; &#49549;&#49457;&#51012; &#44396;&#49457;&#54616;&#45716; &#48169;&#48277;" expand="false"></tocitem>
      <tocitem target="task-webcontainersessiontimeout" text="&#50937; &#52968;&#53580;&#51060;&#45320;&#51032; &#49464;&#49496; &#49549;&#49457;&#51012; &#44396;&#49457;&#54616;&#45716; &#48169;&#48277;" expand="false"></tocitem>
      <tocitem target="task-webcontainermanagerprops" text="&#50937; &#52968;&#53580;&#51060;&#45320;&#51032; &#44288;&#47532;&#51088; &#49549;&#49457;&#51012; &#44396;&#49457;&#54616;&#45716; &#48169;&#48277;" expand="false"></tocitem>
      <tocitem target="task-webcontainerstoreprops" text="&#50937; &#52968;&#53580;&#51060;&#45320;&#51032; &#51200;&#51109;&#49548; &#49549;&#49457;&#51012; &#44396;&#49457;&#54616;&#45716; &#48169;&#48277;" expand="false"></tocitem>
      <tocitem target="task-webcontaineravailability" text="&#50937; &#52968;&#53580;&#51060;&#45320; &#44032;&#50857;&#49457; &#49444;&#51221;&#51012; &#44396;&#49457;&#54616;&#45716; &#48169;&#48277;" expand="false"></tocitem>
    </tocitem>
    <tocitem target="task-group-confighttpservice" text="HTTP &#49436;&#48708;&#49828; &#44396;&#49457;" expand="false">
      <tocitem target="task-accesslog" text="HTTP &#49436;&#48708;&#49828;&#47484; &#44396;&#49457;&#54616;&#45716; &#48169;&#48277;" expand="false"></tocitem>
    </tocitem>
    <tocitem target="task-group-httplisteners" text="HTTP &#47532;&#49828;&#45320; &#44396;&#49457;" expand="false">
      <tocitem target="task-httplistenernew" text="HTTP &#47532;&#49828;&#45320;&#47484; &#49373;&#49457;&#54616;&#45716; &#48169;&#48277;" expand="false"></tocitem>
      <tocitem target="task-httplisteneredit" text="HTTP &#47532;&#49828;&#45320;&#47484; &#54200;&#51665;&#54616;&#45716; &#48169;&#48277;" expand="false"></tocitem>
      <tocitem target="task-httplistenerdelete" text="HTTP &#47532;&#49828;&#45320;&#47484; &#49325;&#51228;&#54616;&#45716; &#48169;&#48277;" expand="false"></tocitem>
      <tocitem target="task-httplistenerssl" text="HTTP &#47532;&#49828;&#45320;&#51032; SSL &#49444;&#51221;&#51012; &#54200;&#51665;&#54616;&#45716; &#48169;&#48277;" expand="false"></tocitem>
    </tocitem>
    <tocitem target="task-group-virtualservers" text="&#44032;&#49345; &#49436;&#48260; &#44396;&#49457;" expand="false">
      <tocitem target="task-virtualservercreate" text="&#44032;&#49345; &#49436;&#48260;&#47484; &#49373;&#49457;&#54616;&#45716; &#48169;&#48277;" expand="false"></tocitem>
      <tocitem target="task-virtualserveredit" text="&#44032;&#49345; &#49436;&#48260;&#47484; &#54200;&#51665;&#54616;&#45716; &#48169;&#48277;" expand="false"></tocitem>
      <tocitem target="task-virtualserverdelete" text="&#44032;&#49345; &#49436;&#48260;&#47484; &#49325;&#51228;&#54616;&#45716; &#48169;&#48277;" expand="false"></tocitem>
    </tocitem>
    <tocitem target="task-group-networkconfig" text="&#45348;&#53944;&#50892;&#53356; &#44396;&#49457;" expand="false">
      <tocitem target="task-networklistenernew" text="&#45348;&#53944;&#50892;&#53356; &#47532;&#49828;&#45320;&#47484; &#49373;&#49457;&#54616;&#45716; &#48169;&#48277;" expand="false"></tocitem>
      <tocitem target="task-networklisteneredit" text="&#45348;&#53944;&#50892;&#53356; &#47532;&#49828;&#45320;&#47484; &#54200;&#51665;&#54616;&#45716; &#48169;&#48277;" expand="false"></tocitem>
      <tocitem target="task-networklistenerdelete" text="&#45348;&#53944;&#50892;&#53356; &#47532;&#49828;&#45320;&#47484; &#49325;&#51228;&#54616;&#45716; &#48169;&#48277;" expand="false"></tocitem>
      <tocitem target="task-protocolnew" text="&#54532;&#47196;&#53664;&#53084;&#51012; &#49373;&#49457;&#54616;&#45716; &#48169;&#48277;" expand="false"></tocitem>
      <tocitem target="task-protocoledit" text="&#54532;&#47196;&#53664;&#53084;&#51012; &#54200;&#51665;&#54616;&#45716; &#48169;&#48277;" expand="false"></tocitem>
      <tocitem target="task-protocolssledit" text="&#54532;&#47196;&#53664;&#53084;&#51032; SSL &#49444;&#51221;&#51012; &#54200;&#51665;&#54616;&#45716; &#48169;&#48277;" expand="false"></tocitem>
      <tocitem target="task-protocolhttpedit" text="&#54532;&#47196;&#53664;&#53084;&#51032; HTTP &#49444;&#51221;&#51012; &#54200;&#51665;&#54616;&#45716; &#48169;&#48277;" expand="false"></tocitem>
      <tocitem target="task-protocolfilecacheedit" text="&#54532;&#47196;&#53664;&#53084;&#51032; &#54028;&#51068; &#52880;&#49884; &#49444;&#51221;&#51012; &#54200;&#51665;&#54616;&#45716; &#48169;&#48277;" expand="false"></tocitem>
      <tocitem target="task-protocoldelete" text="&#54532;&#47196;&#53664;&#53084;&#51012; &#49325;&#51228;&#54616;&#45716; &#48169;&#48277;" expand="false"></tocitem>
      <tocitem target="task-transportnew" text="&#51204;&#49569;&#51012; &#49373;&#49457;&#54616;&#45716; &#48169;&#48277;" expand="false"></tocitem>
      <tocitem target="task-transportedit" text="&#51204;&#49569;&#51012; &#54200;&#51665;&#54616;&#45716; &#48169;&#48277;" expand="false"></tocitem>
      <tocitem target="task-transportdelete" text="&#51204;&#49569;&#51012; &#49325;&#51228;&#54616;&#45716; &#48169;&#48277;" expand="false"></tocitem>
    </tocitem>
    <tocitem target="task-group-threadpools" text="&#49828;&#47112;&#46300; &#54400; &#44396;&#49457;" expand="false">
      <tocitem target="task-threadpoolnew" text="&#49828;&#47112;&#46300; &#54400;&#51012; &#49373;&#49457;&#54616;&#45716; &#48169;&#48277;" expand="false"></tocitem>
      <tocitem target="task-threadpooledit" text="&#49828;&#47112;&#46300; &#54400;&#51012; &#54200;&#51665;&#54616;&#45716; &#48169;&#48277;" expand="false"></tocitem>
      <tocitem target="task-threadpooldelete" text="&#49828;&#47112;&#46300; &#54400;&#51012; &#49325;&#51228;&#54616;&#45716; &#48169;&#48277;" expand="false"></tocitem>
    </tocitem>
  </tocitem>
  <tocitem target="ref-topic-group" text="GlassFish Server &#44288;&#47532; &#53080;&#49556; &#52280;&#51312;&#49436;" expand="false">
    <tocitem target="ref-group-configuration" text="&#44396;&#49457;" expand="false">
      <tocitem target="ref-group-availabilityservice" text="&#44032;&#50857;&#49457; &#49436;&#48708;&#49828;" expand="false">
        <tocitem target="ref-webcontaineravailability" text="&#50937; &#52968;&#53580;&#51060;&#45320; &#44032;&#50857;&#49457;" expand="false"></tocitem>
      </tocitem>
      <tocitem target="ref-group-webcontainer" text="&#50937; &#52968;&#53580;&#51060;&#45320;" expand="false">
        <tocitem target="ref-generalproptab" text="&#51068;&#48152; &#49549;&#49457;" expand="false"></tocitem>
        <tocitem target="ref-webcontainerprops" text="&#50937; &#52968;&#53580;&#51060;&#45320; &#44288;&#47144; &#49549;&#49457;" expand="false"></tocitem>
        <tocitem target="ref-sessionproptab" text="&#49464;&#49496; &#49549;&#49457;" expand="false"></tocitem>
        <tocitem target="ref-websessionproperties" text="&#50937; &#52968;&#53580;&#51060;&#45320; &#49464;&#49496; &#44288;&#47144; &#49549;&#49457;" expand="false"></tocitem>
        <tocitem target="ref-managerproptab" text="&#44288;&#47532;&#51088; &#49549;&#49457;" expand="false"></tocitem>
        <tocitem target="ref-storeproptab" text="&#51200;&#51109;&#49548; &#49549;&#49457;" expand="false"></tocitem>
      </tocitem>
      <tocitem target="ref-group-httpservice" text="HTTP &#49436;&#48708;&#49828;" expand="false">
        <tocitem target="ref-accesslog" text="HTTP &#49436;&#48708;&#49828;" expand="false"></tocitem>
        <tocitem target="ref-httpserviceprops" text="HTTP &#49436;&#48708;&#49828; &#44288;&#47144; &#49549;&#49457;" expand="false"></tocitem>
        <tocitem target="ref-group-httplisteners" text="HTTP &#47532;&#49828;&#45320;" expand="false">
          <tocitem target="ref-httplisteners" text="HTTP &#47532;&#49828;&#45320;" expand="false"></tocitem>
          <tocitem target="ref-httplistenernew" text="&#49352; HTTP &#47532;&#49828;&#45320;" expand="false"></tocitem>
          <tocitem target="ref-httplisteneredit" text="HTTP &#47532;&#49828;&#45320; &#54200;&#51665;" expand="false"></tocitem>
        </tocitem>
      </tocitem>
      <tocitem target="ref-group-virtualservers" text="&#44032;&#49345; &#49436;&#48260;" expand="false">
        <tocitem target="ref-virtualservers" text="&#44032;&#49345; &#49436;&#48260;" expand="false"></tocitem>
        <tocitem target="ref-virtualservernew" text="&#49352; &#44032;&#49345; &#49436;&#48260;" expand="false"></tocitem>
        <tocitem target="ref-virtualserverprops" text="&#44032;&#49345; &#49436;&#48260; &#44288;&#47144; &#49549;&#49457;" expand="false"></tocitem>
        <tocitem target="ref-virtualserveredit" text="&#44032;&#49345; &#49436;&#48260; &#54200;&#51665;" expand="false"></tocitem>
      </tocitem>
      <tocitem target="ref-group-networkconfig" text="&#45348;&#53944;&#50892;&#53356; &#44396;&#49457;" expand="false">
        <tocitem target="ref-networkconfig" text="&#45348;&#53944;&#50892;&#53356; &#44396;&#49457;" expand="false"></tocitem>
        <tocitem target="ref-group-networklisteners" text="&#45348;&#53944;&#50892;&#53356; &#47532;&#49828;&#45320;" expand="false">
          <tocitem target="ref-networklisteners" text="&#45348;&#53944;&#50892;&#53356; &#47532;&#49828;&#45320;" expand="false"></tocitem>
          <tocitem target="ref-networklistenernew" text="&#49352; &#45348;&#53944;&#50892;&#53356; &#47532;&#49828;&#45320;" expand="false"></tocitem>
          <tocitem target="ref-networklisteneredit" text="&#45348;&#53944;&#50892;&#53356; &#47532;&#49828;&#45320; &#54200;&#51665;" expand="false"></tocitem>
        </tocitem>
        <tocitem target="ref-group-protocols" text="&#54532;&#47196;&#53664;&#53084;" expand="false">
          <tocitem target="ref-protocols" text="&#54532;&#47196;&#53664;&#53084;" expand="false"></tocitem>
          <tocitem target="ref-protocolnew" text="&#49352; &#54532;&#47196;&#53664;&#53084;" expand="false"></tocitem>
          <tocitem target="ref-protocoledit" text="&#54532;&#47196;&#53664;&#53084; &#54200;&#51665;" expand="false"></tocitem>
          <tocitem target="ref-protocolssledit" text="SSL" expand="false"></tocitem>
          <tocitem target="ref-protocolhttpedit" text="HTTP" expand="false"></tocitem>
          <tocitem target="ref-protocolfilecacheedit" text="&#54028;&#51068; &#52880;&#49884;" expand="false"></tocitem>
        </tocitem>
        <tocitem target="ref-group-transports" text="&#51204;&#49569;" expand="false">
          <tocitem target="ref-transports" text="&#51204;&#49569;" expand="false"></tocitem>
          <tocitem target="ref-transportnew" text="&#49352; &#51204;&#49569;" expand="false"></tocitem>
          <tocitem target="ref-transportedit" text="&#51204;&#49569; &#54200;&#51665;" expand="false"></tocitem>
        </tocitem>
      </tocitem>
      <tocitem target="ref-group-threadpools" text="&#49828;&#47112;&#46300; &#54400;" expand="false">
        <tocitem target="ref-threadpools" text="&#49828;&#47112;&#46300; &#54400;" expand="false"></tocitem>
        <tocitem target="ref-threadpoolnew" text="&#49352; &#49828;&#47112;&#46300; &#54400;" expand="false"></tocitem>
        <tocitem target="ref-threadpooledit" text="&#49828;&#47112;&#46300; &#54400; &#54200;&#51665;" expand="false"></tocitem>
      </tocitem>
    </tocitem>
  </tocitem>
</toc>
