<toc version="2.0">
  <tocitem target="tasks-topic-group" text="GlassFish Server &#31649;&#29702;&#12467;&#12531;&#12477;&#12540;&#12523;&#12398;&#12479;&#12473;&#12463;" expand="false">
    <tocitem target="task-group-configejbcontainer" text="EJB&#12467;&#12531;&#12486;&#12490;&#12398;&#27083;&#25104;" expand="false">
      <tocitem target="task-ejbmdbpoolsettings" text="" expand="false"></tocitem>
      <tocitem target="task-ejbtimerservice" text="EJB&#12479;&#12452;&#12510;&#12540;&#12539;&#12469;&#12540;&#12499;&#12473;&#12434;&#27083;&#25104;&#12377;&#12427;&#12395;&#12399;" expand="false"></tocitem>
      <tocitem target="task-ejbcontaineravailability" text="EJB&#12467;&#12531;&#12486;&#12490;&#12398;&#21487;&#29992;&#24615;&#35373;&#23450;&#12434;&#27083;&#25104;&#12377;&#12427;&#12395;&#12399;" expand="false"></tocitem>
    </tocitem>
  </tocitem>
  <tocitem target="ref-topic-group" text="GlassFish Server &#31649;&#29702;&#12467;&#12531;&#12477;&#12540;&#12523;&#12398;&#12522;&#12501;&#12449;&#12524;&#12531;&#12473;" expand="false">
    <tocitem target="ref-group-configuration" text="&#27083;&#25104;" expand="false">
      <tocitem target="ref-group-availabilityservice" text="&#21487;&#29992;&#24615;&#12469;&#12540;&#12499;&#12473;" expand="false">
        <tocitem target="ref-ejbcontaineravailability" text="EJB&#12467;&#12531;&#12486;&#12490;&#12398;&#21487;&#29992;&#24615;" expand="false"></tocitem>
      </tocitem>
      <tocitem target="ref-group-ejbcontainer" text="EJB&#12467;&#12531;&#12486;&#12490;" expand="false">
        <tocitem target="ref-ejbmdbpoolsettings" text="MDB&#12487;&#12501;&#12457;&#12523;&#12488;&#12539;&#12503;&#12540;&#12523;&#35373;&#23450;" expand="false"></tocitem>
        <tocitem target="ref-ejbtimerservice" text="EJB&#12479;&#12452;&#12510;&#12540;&#12539;&#12469;&#12540;&#12499;&#12473;" expand="false"></tocitem>
      </tocitem>
    </tocitem>
  </tocitem>
</toc>
